capcalc/__init__.py
capcalc/_version.py
capcalc/filter.py
capcalc/fit.py
capcalc/io.py
capcalc/miscmath.py
capcalc/niftidecomp.py
capcalc/parser_funcs.py
capcalc/stats.py
capcalc/util.py
capcalc/utils.py
capcalc/scripts/behavioralprediction
capcalc/scripts/capcalc_dispatcher.py
capcalc/scripts/capfromany.py
capcalc/scripts/capfromtcs.py
capcalc/scripts/ccspatialdecomp.py
capcalc/scripts/clustercomp.py
capcalc/scripts/clusternifti.py
capcalc/scripts/clustersort.py
capcalc/scripts/fitglm.py
capcalc/scripts/kmeans.py
capcalc/scripts/maptoroi.py
capcalc/scripts/normtcs.py
capcalc/scripts/roidecompose.py
capcalc/scripts/statefiltertest.py
capcalc/scripts/statematch.py
capcalc/scripts/statlasgen.py
capcalc/scripts/supercluster.py
capcalc/scripts/tcfrom3col.py
capcalc/scripts/updatemodel.py
capcalc-1.5.1.2.dist-info/licenses/LICENSE
capcalc-1.5.1.2.dist-info/METADATA
capcalc-1.5.1.2.dist-info/WHEEL
capcalc-1.5.1.2.dist-info/entry_points.txt
capcalc-1.5.1.2.dist-info/top_level.txt
capcalc-1.5.1.2.dist-info/RECORD
