Metadata-Version: 2.4
Name: capcalc
Version: 1.5.1.2
Summary: capcalc is a suite of python programs used to perform coactivation pattern analysis on time series data.
Author-email: Blaise Frederick <blaise.frederick@gmail.com>
License: Apache Software License
Project-URL: Homepage, https://github.com/bbfrederick/capcalc
Project-URL: Bug Tracker, https://github.com/bbfrederick/capcalc/issues
Project-URL: Repository, https://github.com/bbfrederick/capcalc.git
Project-URL: Documentation, https://capcalc.readthedocs.io
Project-URL: Changelog, https://github.com/bbfrederick/capcalc/blob/main/CHANGELOG.md
Keywords: fMRI,temporal dynamics
Classifier: Operating System :: OS Independent
Classifier: Development Status :: 5 - Production/Stable
Classifier: Intended Audience :: Science/Research
Classifier: Topic :: Scientific/Engineering :: Image Recognition
Classifier: License :: OSI Approved :: Apache Software License
Classifier: Programming Language :: Python :: 3.9
Classifier: Programming Language :: Python :: 3.10
Classifier: Programming Language :: Python :: 3.11
Classifier: Programming Language :: Python :: 3.12
Requires-Python: >=3.9
License-File: LICENSE
Requires-Dist: numpy
Requires-Dist: scipy
Requires-Dist: scikit-learn
Requires-Dist: matplotlib
Requires-Dist: statsmodels
Requires-Dist: nibabel
Requires-Dist: versioneer
Provides-Extra: test
Requires-Dist: codecov; extra == "test"
Requires-Dist: coverage; extra == "test"
Requires-Dist: coveralls; extra == "test"
Requires-Dist: flake8-black; extra == "test"
Requires-Dist: pytest; extra == "test"
Requires-Dist: pytest-cov; extra == "test"
Provides-Extra: doc
Requires-Dist: sphinx; extra == "doc"
Requires-Dist: sphinx_rtd_theme; extra == "doc"
Requires-Dist: sphinx-argparse; extra == "doc"
Requires-Dist: sphinx-gallery; extra == "doc"
Requires-Dist: myst-parser; extra == "doc"
Requires-Dist: numpydoc; extra == "doc"
Requires-Dist: sphinxcontrib-bibtex; extra == "doc"
Requires-Dist: tomlkit; extra == "doc"
Dynamic: license-file
